MANIFEST.in
README.rst
setup.py
doc/__init__.py
doc/conf.py
doc/solarized.py
sheepdog_tables/__init__.py
sheepdog_tables/column.py
sheepdog_tables/filters.py
sheepdog_tables/forms.py
sheepdog_tables/mixins.py
sheepdog_tables/models.py
sheepdog_tables/paginator.py
sheepdog_tables/table.py
sheepdog_tables/utils.py
sheepdog_tables.egg-info/PKG-INFO
sheepdog_tables.egg-info/SOURCES.txt
sheepdog_tables.egg-info/dependency_links.txt
sheepdog_tables.egg-info/top_level.txt
sheepdog_tables/static/tables/js/binding.coffee
sheepdog_tables/static/tables/js/filtering.coffee
sheepdog_tables/static/tables/js/jquery.ba-bbq.js
sheepdog_tables/templates/tables/edittable.html
sheepdog_tables/templates/tables/edittable_row.html
sheepdog_tables/templates/tables/edittable_submit.html
sheepdog_tables/templates/tables/pagination_controls.html
sheepdog_tables/templates/tables/table.html
sheepdog_tables/templates/tables/table_row.html
sheepdog_tables/templatetags/__init__.py
sheepdog_tables/templatetags/call.py
sheepdog_tables/templatetags/get.py
sheepdog_tables/templatetags/urlbuilder.py