Metadata-Version: 1.0
Name: sheepdog-tables
Version: 1.2.0
Summary: Easy to use tables API for Django
Home-page: https://github.com/SheepDogInc/sheepdog_tables
Author: Alex Hart, Adam Thurlow, Karl Leuschen
Author-email: exallium@gmail.com, adam@sheepdog.com, karl@sheepdog.com
License: BSD
Keywords: tables
Platform: UNKNOWN
Classifier: Environment :: Web Environment
Classifier: Framework :: Django
Classifier: License :: OSI Approved :: BSD License
Classifier: Operating System :: OS Independent
Classifier: Programming Language :: Python
Classifier: Topic :: Software Development :: Libraries :: Python Modules
